depcycle/__init__.py
depcycle/__main__.py
depcycle/cli.py
depcycle/config.py
depcycle/graph/__init__.py
depcycle/graph/dependency_graph.py
depcycle/graph/module_node.py
depcycle/parsing/__init__.py
depcycle/parsing/ast_parser.py
depcycle/parsing/project.py
depcycle/rendering/__init__.py
depcycle/rendering/interface.py
depcycle/rendering/visualizers.py
depcycle-0.2.5.dist-info/licenses/LICENSE
depcycle-0.2.5.dist-info/METADATA
depcycle-0.2.5.dist-info/WHEEL
depcycle-0.2.5.dist-info/entry_points.txt
depcycle-0.2.5.dist-info/top_level.txt
depcycle-0.2.5.dist-info/RECORD
