Metadata-Version: 2.4
Name: depcycle
Version: 0.2.5
Summary: Command-line tool to visualize Python project dependencies.
Author: DepCycle Maintainers
License: MIT License
Project-URL: Homepage, https://github.com/Matricess/depcycle
Project-URL: Repository, https://github.com/Matricess/depcycle
Project-URL: Issues, https://github.com/Matricess/depcycle/issues
Keywords: dependencies,graphviz,architecture,visualization,cli
Classifier: Development Status :: 3 - Alpha
Classifier: Environment :: Console
Classifier: Intended Audience :: Developers
Classifier: License :: OSI Approved :: MIT License
Classifier: Operating System :: OS Independent
Classifier: Programming Language :: Python
Classifier: Programming Language :: Python :: 3
Classifier: Programming Language :: Python :: 3.8
Classifier: Programming Language :: Python :: 3.9
Classifier: Programming Language :: Python :: 3.10
Classifier: Programming Language :: Python :: 3.11
Classifier: Programming Language :: Python :: 3.12
Classifier: Topic :: Software Development :: Build Tools
Classifier: Topic :: Software Development :: Testing
Classifier: Topic :: Utilities
Requires-Python: >=3.8
License-File: LICENSE
Requires-Dist: graphviz>=0.20.0
Provides-Extra: dev
Requires-Dist: pytest>=7.0; extra == "dev"
Dynamic: license-file
